skill_hub/__init__.py
skill_hub/__main__.py
skill_hub/commands/__init__.py
skill_hub/commands/install.py
skill_hub/commands/list.py
skill_hub/commands/manage.py
skill_hub/commands/mng.py
skill_hub/commands/search.py
skill_hub/commands/sync.py
skill_hub/commands/uninstall.py
skill_hub/commands/update.py
skill_hub/utils/__init__.py
skill_hub/utils/agent_cmd.py
skill_hub/utils/skill_mng.py
skills_hub-1.0.6.dist-info/licenses/LICENSE
skills_hub-1.0.6.dist-info/METADATA
skills_hub-1.0.6.dist-info/WHEEL
skills_hub-1.0.6.dist-info/entry_points.txt
skills_hub-1.0.6.dist-info/top_level.txt
skills_hub-1.0.6.dist-info/RECORD
